{
    "broadcast_port" : "tcp://*:37013",
    "subscription_port" : "tcp://localhost:37012",
    "use_prefect" : false,
    "reconstruction_deployment": "Reconstruct From .cxi/reconstruct-from-cxi",
    "succinct" : false,
    "compression" : "lzf",
    "chunk_size" : 10,
    "device" : "cuda:0",
    "interpolate" : false,
    "center" : [ 480, 480 ],
    "output_pixel_size" : 10,
    "output_pixel_count" : 960,
    "binning_factor" : 1,
    "cut_zeros": true,
    "background_offset": 0.55,
    "background_median_width": 10,
    "max_overscan_correction": 50,
    "min_overscan_correction": -1000,
    "shear" : [[ 0.99961877, -0.06551266],
               [ 0.02651655,  0.99879594]],
    "dp_fraction_for_illumination_init": 0.1,
    "zmq_metadata_timeout": 1.0,
    "zmq_data_timeout": 0.01
}
